asposeomrcloud/__init__.py
asposeomrcloud/api_client.py
asposeomrcloud/configuration.py
asposeomrcloud/rest.py
asposeomrcloud/apis/__init__.py
asposeomrcloud/apis/omr_api.py
asposeomrcloud/apis/storage_api.py
asposeomrcloud/models/__init__.py
asposeomrcloud/models/base_model.py
asposeomrcloud/models/disc_usage.py
asposeomrcloud/models/error.py
asposeomrcloud/models/error_details.py
asposeomrcloud/models/file_info.py
asposeomrcloud/models/file_version.py
asposeomrcloud/models/file_versions.py
asposeomrcloud/models/files_list.py
asposeomrcloud/models/files_upload_result.py
asposeomrcloud/models/object_exist.py
asposeomrcloud/models/omr_error_response.py
asposeomrcloud/models/omr_function_param.py
asposeomrcloud/models/omr_response.py
asposeomrcloud/models/omr_response_content.py
asposeomrcloud/models/omr_response_details.py
asposeomrcloud/models/omr_response_info.py
asposeomrcloud/models/payload.py
asposeomrcloud/models/recognition_statistics.py
asposeomrcloud/models/server_stat.py
asposeomrcloud/models/storage_exist.py
asposeomrcloud/models/storage_file.py
demo/__init__.py
demo/omr_demo.py
demo/run_demo.py
test/__init__.py
test/test_helper.py
test/test_omr.py
aspose_omr_cloud-20.10.dist-info/LICENSE
aspose_omr_cloud-20.10.dist-info/METADATA
aspose_omr_cloud-20.10.dist-info/WHEEL
aspose_omr_cloud-20.10.dist-info/top_level.txt
aspose_omr_cloud-20.10.dist-info/RECORD
