Metadata-Version: 2.1
Name: aspose-omr-cloud
Version: 20.10
Summary: Aspose.OMR Cloud SDK
Home-page: https://github.com/aspose-omr-cloud/aspose-omr-cloud-python
Author: Aspose Pty Ltd
Author-email: aspose.cloud@asposeptyltd.com
License: MIT
Keywords: Aspose.OMR Cloud API Reference,Aspose,OMR,OMR Cloud
Platform: UNKNOWN
Classifier: Development Status :: 5 - Production/Stable
Classifier: Intended Audience :: Developers
Classifier: License :: OSI Approved :: MIT License
Classifier: Programming Language :: Python :: 3.6
Classifier: Programming Language :: Python :: 3.7
Classifier: Programming Language :: Python :: 3.8
Classifier: Programming Language :: Python :: 3.9
Classifier: Topic :: Software Development :: Libraries :: Python Modules
Classifier: Operating System :: OS Independent
Requires-Dist: urllib3 (>=1.15)
Requires-Dist: six (>=1.10)
Requires-Dist: certifi
Requires-Dist: pyopenssl
Requires-Dist: idna
Requires-Dist: urllib3[secure]
Requires-Dist: python-dateutil
Requires-Dist: requests[security]
